dpyecm/__init__.py
dpyecm-0.1.0.dist-info/LICENSE
dpyecm-0.1.0.dist-info/METADATA
dpyecm-0.1.0.dist-info/WHEEL
dpyecm-0.1.0.dist-info/top_level.txt
dpyecm-0.1.0.dist-info/RECORD
