Metadata-Version: 2.1
Name: dpyecm
Version: 0.1.0
Summary: Force the discord.py command framework to correspond to the slashes.
Home-page: UNKNOWN
Author: tasuren
Author-email: tasuren@aol.com
License: MIT
Project-URL: Documentation, https://tasuren.github.io/dpyecm
Project-URL: Donate, https://www.buymeacoffee.com/tasuren
Project-URL: Source Code, https://github.com/tasuren/dpyecm
Project-URL: Chat, https://discord.gg/kfMwZUyGFG
Keywords: discord discord.py
Platform: UNKNOWN
Classifier: Programming Language :: Python :: 3.10
Requires-Python: >=3.10.0
License-File: LICENSE
